{
  "texto_id": "texto",
  "etiqueta_original": "derecha",
  "perfil_global_del_texto": {
    "score_promedio": 0.6,
    "interpretacion": "derecha moderada"
  },
  "frases": [
    {
      "frase": "Porque la ruleta rusa es eso, es el juego de la muerte.",
      "score": 0.5,
      "etiqueta": "neutral"
    },
    {
      "frase": "A mí no me importa, en serio, si él es de La Cámpora, es de acá, no me importa de dónde es.",
      "score": 0.5,
      "etiqueta": "neutral"
    },
    {
      "frase": "Conclusión: el gobernador premia a los fiscales garantistas que liberan asesinos y delincuentes.",
      "score": 0.8,
      "etiqueta": "derecha"
    },
    {
      "frase": "El que agarra un arma y mata es un criminal.",
      "score": 0.7,
      "etiqueta": "derecha"
    },
    {
      "frase": "El que tira y mata a una nena de 7 años es un mal nacido que merece el peor sufrimiento posible.",
      "score": 0.9,
      "etiqueta": "ultraderecha"
    },
    {
      "frase": "El ladrón es una víctima del sistema.",
      "score": 0.1,
      "etiqueta": "izquierda"
    },
    {
      "frase": "El orden no es de derecha, no es de izquierda, es orden.",
      "score": 0.6,
      "etiqueta": "neutral"
    },
    {
      "frase": "Una policía firme que aniquile la delincuencia no es de derecha.",
      "score": 0.8,
      "etiqueta": "derecha"
    },
    {
      "frase": "Se trata simplemente de no querer vivir en una ruleta rusa.",
      "score": 0.5,
      "etiqueta": "neutral"
    }
  ],
  "tokens_procesados": 4841
}